LICENSE
MANIFEST.in
README.md
setup.py
Eel.egg-info/PKG-INFO
Eel.egg-info/SOURCES.txt
Eel.egg-info/dependency_links.txt
Eel.egg-info/requires.txt
Eel.egg-info/top_level.txt
eel/__init__.py
eel/__main__.py
eel/browsers.py
eel/chrome.py
eel/edge.py
eel/eel.js
eel/electron.py
eel/msIE.py
eel/py.typed
eel/types.py