Metadata-Version: 2.2
Name: Eel
Version: 0.18.2
Summary: For little HTML GUI applications, with easy Python/JS interop
Home-page: https://github.com/python-eel/Eel
Author: Python Eel Organisation
Author-email: python-eel@protonmail.com
Keywords: gui,html,javascript,electron
Classifier: Development Status :: 3 - Alpha
Classifier: Natural Language :: English
Classifier: Operating System :: MacOS
Classifier: Operating System :: POSIX
Classifier: Operating System :: Microsoft :: Windows :: Windows 10
Classifier: Programming Language :: Python :: 3
Classifier: Programming Language :: Python :: 3.7
Classifier: Programming Language :: Python :: 3.8
Classifier: Programming Language :: Python :: Implementation :: CPython
Classifier: License :: OSI Approved :: MIT License
Requires-Python: >=3.7
License-File: LICENSE
Requires-Dist: bottle
Requires-Dist: bottle-websocket
Requires-Dist: future
Requires-Dist: pyparsing
Requires-Dist: typing_extensions
Requires-Dist: importlib_resources
Provides-Extra: jinja2
Requires-Dist: jinja2>=2.10; extra == "jinja2"
Dynamic: author
Dynamic: author-email
Dynamic: classifier
Dynamic: description
Dynamic: description-content-type
Dynamic: home-page
Dynamic: keywords
Dynamic: provides-extra
Dynamic: requires-dist
Dynamic: requires-python
Dynamic: summary
